Informe2/Semisumador.v
module Semisumador (
  input A,
  input B,
  output Y,
  output X
);
  assign Y = (B ^ A);
  assign X = (A & B);
endmodule

Informe2/Sumador.v
module Sumador (
  input A,
  input B,
  input CIn,
  output COut,
  output Sum
);
  wire s0;
  wire s1;
  wire s2;
  Semisumador Semisumador_0 (A,B,s0,s1);
  Semisumador Semisumador_1 (s0,CIn,Sum,s2);
  assign COut = (s2 | s1);
endmodule

Informe2/Archivos Verilog/sumador_tb.v
module testbech;
 reg [2:0] inputs;
  integer i;
  initial
  begin
  for (i=0; i<8; i=i+1)
  begin
  inputs = i;
  #1;
  end
  end
  
  wire [1:0] outs;
  // DEVICE/DESIGN UNDER TEST
  Sumador dut (
    .B(inputs[2]), .A(inputs[1]), .CIn(inputs[0]),
    .COut(outs[1]), .Sum(outs[0])
  );

  // MONITOR
  // initial
  //   $monitor("Time: %t, a = %d, b = %d => out = %d",
  //     $time, a, b, value);

  // WAVES IN VCD TO OPEN IN GTKWAVE
  initial
  begin
    $dumpfile("suma.vcd");
    $dumpvars(0, testbech);
  end

endmodule

Informe2/Archivos Verilog/suma.vcd
$date
	Tue Sep 19 12:16:48 2023
$end
$version
	Icarus Verilog
$end
$timescale
	1s
$end
$scope module testbech $end
$var wire 2 ! outs [1:0] $end
$var reg 3 " inputs [2:0] $end
$var integer 32 # i [31:0] $end
$scope module dut $end
$var wire 1 $ A $end
$var wire 1 % B $end
$var wire 1 & CIn $end
$var wire 1 ' COut $end
$var wire 1 ( s2 $end
$var wire 1 ) s1 $end
$var wire 1 * s0 $end
$var wire 1 + Sum $end
$scope module Semisumador_0 $end
$var wire 1 $ A $end
$var wire 1 % B $end
$var wire 1 ) X $end
$var wire 1 * Y $end
$upscope $end
$scope module Semisumador_1 $end
$var wire 1 * A $end
$var wire 1 & B $end
$var wire 1 ( X $end
$var wire 1 + Y $end
$upscope $end
$upscope $end
$upscope $end
$enddefinitions $end
$comment Show the parameter values. $end
$dumpall
$end
#0
$dumpvars
0+
0*
0)
0(
0'
0&
0%
0$
b0 #
b0 "
b0 !
$end
#1
b1 !
1+
1&
b1 "
b1 #
#2
1*
b1 !
1+
1$
0&
b10 "
b10 #
#3
1'
b10 !
0+
1(
1&
b11 "
b11 #
#4
0'
b1 !
1+
0(
0$
1%
0&
b100 "
b100 #
#5
1'
b10 !
0+
1(
1&
b101 "
b101 #
#6
0*
1)
b10 !
0+
0(
1$
0&
b110 "
b110 #
#7
b11 !
1+
1&
b111 "
b111 #
#8
b1000 #
